MANIFEST.in
README.md
requirements.txt
setup.py
version.txt
specular/__init__.py
specular/specular.py
specular/test_acceptance.py
specular.egg-info/PKG-INFO
specular.egg-info/SOURCES.txt
specular.egg-info/dependency_links.txt
specular.egg-info/requires.txt
specular.egg-info/top_level.txt