Metadata-Version: 1.0
Name: specular
Version: 0.4a4
Summary: Specular specification toolkit
Home-page: UNKNOWN
Author: GRNET S.A.
Author-email: team@dev.grnet.gr
License: Affero GPL v3
Platform: UNKNOWN
